Workbook

Sheet Cover page
C2: Nike Financial Model | H2: Analysis Period: 2023A - 2030E
B5: Scenario Analysis | E5: General Settings | H5: Table of Contents
B7: Live Scenario | C7: 1 | E7: Company Name | F7: Nike | H7: Cover Page
E8: Company Ticker | F8: ABC | H8: Income Statement
B9: Alerts | E9: Currency | F9: USD | H9: Balance Sheet
E10: Last Update | F10: 45870 | H10: Cash Flow Statement
B11: Balance Sheet Balances? | E11: Contact | F11: Johnson | H11: Assumptions & Drivers

Sheet End Forecast
B2: Income Statement of Nike
D3: 2023 | E3: 2024 | F3: 2025 | G3: 2026 | H3: 2027 | I3: 2028 | J3: 2029 | K3: 2030
B4: Revenue | D4: 5210 | E4: 5435 | F4: 5710 | G4: 5863.5538 | H4: 6021.2369 | I4: 6183.1605 | J4: 6349.4385 | K4: 6520.1881
B5: COGS | D5: 3345 | E5: 3350 | F5: 3551 | G5: 3675.0826 | H5: 3773.9132 | I5: 3875.4016 | J5: 3979.6192 | K5: 4086.6394
B6: Gross Profit | D6: 1865 | E6: 2085 | F6: 2159 | G6: 2188.4712 | H6: 2247.3237 | I6: 2307.7589 | J6: 2369.8193 | K6: 2433.5487
B7: Selling general and Administrative Expense | D7: 850 | E7: 870 | F7: 900 | G7: 939.80962 | H7: 965.08306 | I7: 991.03615 | J7: 1017.6872 | K7: 1045.0549
B8: Research and Development | D8: 400 | E8: 420 | F8: 400 | G8: 438.017 | H8: 449.79619 | I8: 461.89215 | J8: 474.31339 | K8: 487.06866
B9: Operating Income | D9: 615 | E9: 795 | F9: 859 | G9: 810.64452 | H9: 832.44444 | I9: 854.8306 | J9: 877.81877 | K9: 901.42514
B10: Other income/ (Expense), net | D10: 50 | E10: 50 | F10: 50 | G10: 50 | H10: 50 | I10: 50 | J10: 50 | K10: 50
B11: pre-tax-income | D11: 565 | E11: 745 | F11: 809 | G11: 760.64452 | H11: 782.44444 | I11: 804.8306 | J11: 827.81877 | K11: 851.42514
B12: Taxes | D12: 227.5 | E12: 186.25 | F12: 147.25 | G12: 190.16113 | H12: 195.61111 | I12: 201.20765 | J12: 206.95469 | K12: 212.85629
B13: Net income | D13: 337.5 | E13: 558.75 | F13: 661.75 | G13: 570.48339 | H13: 586.83333 | I13: 603.62295 | J13: 620.86408 | K13: 638.56886
B16: Income Statement Assumptions
B18: Revenue Growth Rate | E18: =E4/D4-1 -> 0.04318618 | F18: =F4/E4-1 -> 0.050597976 | G18: =CHOOSE('Cover page'!$C$7,'End Forecast'!G27,'End Forecast'!G28,'End Forecast'!G29) -> 0.066892078 | H18: =CHOOSE('Cover page'!$C$7,'End Forecast'!H27,'End Forecast'!H28,'End Forecast'!H29) -> 0.078745027 | I18: =CHOOSE('Cover page'!$C$7,'End Forecast'!I27,'End Forecast'!I28,'End Forecast'!I29) -> 0.072818553 | J18: =CHOOSE('Cover page'!$C$7,'End Forecast'!J27,'End Forecast'!J28,'End Forecast'!J29) -> 0.07578179 | K18: =CHOOSE('Cover page'!$C$7,'End Forecast'!K27,'End Forecast'!K28,'End Forecast'!K29) -> 0.074300171
B19: COGS as a % of Revenue | D19: =D5/D4 -> 0.64203455 | E19: =E5/E4 -> 0.61637534 | F19: =F5/F4 -> 0.62189142 | G19: =AVERAGE(D19:F19) -> 0.6267671 | H19: =AVERAGE(E19:G19) -> 0.62167796 | I19: =AVERAGE(F19:H19) -> 0.62344549 | J19: =AVERAGE(G19:I19) -> 0.62396352 | K19: =AVERAGE(H19:J19) -> 0.62302899
B20: SG$A as % of Revenue | D20: =D7/D4 -> 0.16314779 | E20: =E7/E4 -> 0.1600736 | F20: =F7/F4 -> 0.15761821 | G20: =AVERAGE(D20:F20) -> 0.16027987 | H20: =AVERAGE(E20:G20) -> 0.15932389 | I20: =AVERAGE(F20:H20) -> 0.15907399 | J20: =AVERAGE(G20:I20) -> 0.15955925 | K20: =AVERAGE(H20:J20) -> 0.15931904
B21: R$D as % of Revenue | D21: =D8/D4 -> 0.076775432 | E21: =E8/E4 -> 0.077276909 | F21: =F8/F4 -> 0.070052539 | G21: =AVERAGE(D21:F21) -> 0.074701627 | H21: =AVERAGE(E21:G21) -> 0.074010358 | I21: =AVERAGE(F21:H21) -> 0.072921508 | J21: =AVERAGE(G21:I21) -> 0.073877831 | K21: =AVERAGE(H21:J21) -> 0.073603233
B22: Other Income / (Expense), net | D22: 50 | E22: 50 | F22: 50 | G22: 50 | H22: 50 | I22: 50 | J22: 50 | K22: 50
B23: Tax rate | D23: 0.25 | E23: 0.25 | F23: 0.25 | G23: 0.25 | H23: 0.25 | I23: 0.25 | J23: 0.25 | K23: 0.25
B26: Revenue Scenarios
B27: Best Case | G27: =G28+2% -> 0.066892078 | H27: =H28+2% -> 0.078745027 | I27: =I28+2% -> 0.072818553 | J27: =J28+2% -> 0.07578179 | K27: =K28+2% -> 0.074300171
B28: Base Case | G28: =AVERAGE(E18:F18) -> 0.046892078 | H28: =AVERAGE(F18:G18) -> 0.058745027 | I28: =AVERAGE(G28:H28) -> 0.052818553 | J28: =AVERAGE(H28:I28) -> 0.05578179 | K28: =AVERAGE(I28:J28) -> 0.054300171
B29: Worst Case | G29: =G28-2% -> 0.026892078 | H29: =H28-2% -> 0.038745027 | I29: =I28-2% -> 0.032818553 | J29: =J28-2% -> 0.03578179 | K29: =K28-2% -> 0.034300171
